tor_async_util/__init__.py
tor_async_util/jsonschemas.py
tor_async_util/jsonschemas/get_health_response.json
tor_async_util/jsonschemas/get_noop_response.json
tor_async_util/jsonschemas/get_version_response.json
tor_async_util-1.15.0.dist-info/LICENSE.md
tor_async_util-1.15.0.dist-info/METADATA
tor_async_util-1.15.0.dist-info/WHEEL
tor_async_util-1.15.0.dist-info/top_level.txt
tor_async_util-1.15.0.dist-info/RECORD
