Metadata-Version: 2.1
Name: tor-async-util
Version: 1.15.0
Summary: Tornado Async Utilities
Home-page: https://github.com/simonsdave/tor-async-util
Author: Dave Simons
Author-email: simonsdave@gmail.com
Maintainer: Dave Simons
Maintainer-email: simonsdave@gmail.com
License: MIT
Download-URL: https://github.com/simonsdave/tor-async-util/tarball/v1.15.0
Keywords: tornado
Platform: UNKNOWN
Classifier: Development Status :: 5 - Production/Stable
Classifier: Intended Audience :: Developers
Classifier: Natural Language :: English
Classifier: License :: OSI Approved :: MIT License
Classifier: Operating System :: OS Independent
Classifier: Programming Language :: Python
Classifier: Programming Language :: Python :: 2.7
Classifier: Programming Language :: Python :: Implementation :: CPython
Classifier: Topic :: Software Development :: Libraries :: Python Modules
Requires-Dist: jsonschema (>=2.5.0)
Requires-Dist: python-keyczar (==0.716)
Requires-Dist: pycurl (>=7.43)
